ezstruct/__init__.py
ezstruct/byte_order.py
ezstruct/delimiter.py
ezstruct/errors.py
ezstruct/field.py
ezstruct/field_transform.py
ezstruct/field_type.py
ezstruct/struct.py
ezstruct-0.1.0.dist-info/DESCRIPTION.rst
ezstruct-0.1.0.dist-info/METADATA
ezstruct-0.1.0.dist-info/pydist.json
ezstruct-0.1.0.dist-info/RECORD
ezstruct-0.1.0.dist-info/top_level.txt
ezstruct-0.1.0.dist-info/WHEEL
