Metadata-Version: 2.0
Name: ezstruct
Version: 0.1.0
Summary: Expressive syntax for working with binary data formats and network protocols.
Home-page: http://github.com/matthewg/EzStruct/
Author: Matthew Sachs
Author-email: matthewg@zevils.com
License: Apache
Platform: UNKNOWN
Classifier: Development Status :: 3 - Alpha
Classifier: Intended Audience :: Developers
Classifier: Natural Language :: English
Classifier: License :: OSI Approved :: Apache Software License
Classifier: Operating System :: OS Independent
Classifier: Programming Language :: Python
Classifier: Programming Language :: Python :: 2
Classifier: Programming Language :: Python :: 2.7
Classifier: Programming Language :: Python :: 3
Classifier: Programming Language :: Python :: 3.3
Classifier: Topic :: Software Development :: Libraries :: Python Modules
Requires-Dist: six
